dynamic/__init__.py
dynamic/__main__.py
dynamic/api_test.py
dynamic/error.py
dynamic/markdown.py
dynamic/notion.py
dynamic/save.py
dynamic/search.py
dynamic/settings.py
dynamic/update.py
dynamic/utility.py
dynamic_cli-1.1.dist-info/LICENSE
dynamic_cli-1.1.dist-info/METADATA
dynamic_cli-1.1.dist-info/WHEEL
dynamic_cli-1.1.dist-info/entry_points.txt
dynamic_cli-1.1.dist-info/top_level.txt
dynamic_cli-1.1.dist-info/RECORD
