Metadata-Version: 2.1
Name: dynamic-cli
Version: 1.1
Summary: A Modern, user-friendly command-line HTTP client for the API testing, and if you're stuck - Search and browse StackOverflow without leaving the CLI
Home-page: https://github.com/IndianOpenSourceFoundation/dynamic-cli
Author: IOSF Community
Author-email: ping@iosf.in
License: UNKNOWN
Project-URL: Bug Tracker, https://github.com/IndianOpenSourceFoundation/dynamic-cli/issues
Platform: UNKNOWN
Classifier: Programming Language :: Python :: 3
Classifier: License :: OSI Approved :: MIT License
Classifier: Operating System :: OS Independent
Requires-Python: >=3.6
License-File: LICENSE
Requires-Dist: certifi (==2020.6.20)
Requires-Dist: chardet (==3.0.4)
Requires-Dist: idna (==2.10)
Requires-Dist: requests (==2.24.0)
Requires-Dist: termcolor (==1.1.0)
Requires-Dist: urllib3 (==1.25.10)
Requires-Dist: rich (==9.9.0)
Requires-Dist: oauthlib (==3.1.0)
Requires-Dist: requests-oauthlib (==1.3.0)
Requires-Dist: colorama (==0.4.4)
Requires-Dist: configparser (==5.0.2)
Requires-Dist: crayons (==0.4.0)
Requires-Dist: selenium (==3.141.0)
Requires-Dist: webdriver-manager (==3.3.0)
Requires-Dist: simple-term-menu (==1.0.1)
